timeit_decorator/__init__.py
timeit_decorator/__main__.py
timeit_decorator/async_wrapper.py
timeit_decorator/sync_wrapper.py
timeit_decorator/timeit.py
timeit_decorator-2.1.3.dist-info/licenses/LICENSE
timeit_decorator-2.1.3.dist-info/METADATA
timeit_decorator-2.1.3.dist-info/WHEEL
timeit_decorator-2.1.3.dist-info/entry_points.txt
timeit_decorator-2.1.3.dist-info/top_level.txt
timeit_decorator-2.1.3.dist-info/RECORD
