Metadata-Version: 2.4
Name: timeit_decorator
Version: 2.1.3
Summary: A versatile timing decorator
Author-email: jubnl <jgunther021@gmail.com>
Maintainer-email: jubnl <jgunther021@gmail.com>
License-Expression: MIT
Project-URL: Homepage, https://github.com/jubnl/timeit_decorator
Project-URL: Repository, https://github.com/jubnl/timeit_decorator
Project-URL: Documentation, https://github.com/jubnl/timeit_decorator/blob/main/README.md
Project-URL: Issues, https://github.com/jubnl/timeit_decorator/issues
Keywords: timing,performance,decorator,profiling
Classifier: Development Status :: 5 - Production/Stable
Classifier: Intended Audience :: Developers
Classifier: Topic :: Software Development :: Libraries
Classifier: Programming Language :: Python :: 3
Classifier: Programming Language :: Python :: 3.7
Classifier: Programming Language :: Python :: 3.8
Classifier: Programming Language :: Python :: 3.9
Classifier: Programming Language :: Python :: 3.10
Classifier: Programming Language :: Python :: 3.11
Classifier: Programming Language :: Python :: 3.12
Classifier: Operating System :: OS Independent
Requires-Python: >=3.7
License-File: LICENSE
Requires-Dist: tabulate>=0.9.0
Provides-Extra: test
Requires-Dist: pytest; extra == "test"
Requires-Dist: pytest-cov; extra == "test"
Requires-Dist: pytest-asyncio; extra == "test"
Dynamic: license-file
